[
  {
    "name": "清月",
    "sex": "皆可",
    "desc": "取自“清月出岭”，意指像皎洁的月光一样纯净、明亮，品格高洁，寓意光明和美好。"
  },
  {
    "name": "天明",
    "sex": "皆可",
    "desc": "取自“天明独去”，意指黎明，象征希望、新的开始和光明的前程。"
  },
  {
    "name": "涧碧",
    "sex": "女",
    "desc": "取自“山红涧碧”，描绘山间清澈碧绿的溪流，寓意自然的美丽、清新和生机勃勃。"
  },
  {
    "name": "烂漫",
    "sex": "皆可",
    "desc": "取自“纷烂漫”，形容自然景色的繁盛茂密，引申为天真、活泼、无拘无束的个性，寓意生命力旺盛。"
  },
  {
    "name": "支子",
    "sex": "女",
    "desc": "取自“芭蕉叶大支子肥”，指植物果实肥大，象征生命力、丰饶和美好圆满。"
  },
  {
    "name": "清扉",
    "sex": "皆可",
    "desc": "由“清月出岭光入扉”中“清”和“扉”组合，意指明净的门户，象征敞开心扉，迎接光明与机遇，心境澄澈。"
  },
  {
    "name": "山漫",
    "sex": "皆可",
    "desc": "由诗句首字“山”和“山红涧碧纷烂漫”中“漫”组合，意指广阔无边的山景，象征心胸开阔，气度宏大，生命力充沛。"
  },
  {
    "name": "天乐",
    "sex": "皆可",
    "desc": "由“天明独去无道路”中“天”和“人生如此自可乐”中“乐”组合，意指上天赐予的快乐，象征知足常乐，心境平和喜悦。"
  },
  {
    "name": "微路",
    "sex": "皆可",
    "desc": "由“山石荦确行径微”中“微”和“天明独去无道路”中“路”组合，意指微小或不显眼的道路，寓意不随大流，走出自己的独特道路，深邃而有内涵。"
  },
  {
    "name": "飞归",
    "sex": "皆可",
    "desc": "由“黄昏到寺蝙蝠飞”中“飞”和“安得至老不更归”中“归”组合，意指自由自在地回归，象征心之所向，来去自如，最终找到平静与归宿。"
  }
]