[
  {
    "name": "万里",
    "sex": "男",
    "desc": "取自“羇危万里身”。意指志向高远，前程万里，气魄宏大，适合男孩，寄托了父母希望孩子有广阔前途的愿望。"
  },
  {
    "name": "明日",
    "sex": "皆可",
    "desc": "取自“明日岁华新”。寓意充满希望，期待美好的未来，每天都有新的开始和进步，适合寄托积极向上的愿景。"
  },
  {
    "name": "岁华",
    "sex": "女",
    "desc": "取自“明日岁华新”。原指年华、岁月，常用来形容美好的时光或青春。用作人名，寄托了希望人生美好、年华绚烂的祝福。"
  },
  {
    "name": "明春",
    "sex": "皆可",
    "desc": "“明”取自“明日岁华新”的开头，意为光明、希望；“春”取自“孤烛异乡春”的结尾，意为生机、活力。组合寓意光明美好的春天或充满希望的新开始。"
  },
  {
    "name": "渐春",
    "sex": "女",
    "desc": "“渐”取自“渐与骨肉远”的开头，意为逐渐、慢慢地；“春”取自“孤烛异乡春”的结尾，意为希望、生机。组合寓意希望逐渐到来，人生充满韧性与希望，迎接美好的未来。"
  }
]