[
  {
    "name": "清风",
    "sex": "男女皆可",
    "desc": "取自“阴气晦昧无清风”。清风象征清新、纯净、洒脱，寓意为人品格高洁，心胸开阔。"
  },
  {
    "name": "正直",
    "sex": "男女皆可",
    "desc": "取自“岂非正直能感通”。正直意为公正无私、品行端正，寓意为人光明磊落，有原则。"
  },
  {
    "name": "青空",
    "sex": "男女皆可",
    "desc": "取自“仰见突兀撑青空”。青空象征广阔、清澈、高远，寓意为人志向远大，心境开阔明朗。"
  },
  {
    "name": "松柏",
    "sex": "男女皆可",
    "desc": "取自“松柏一迳趋灵宫”。松柏象征坚韧不拔、长寿、高尚，寓意为人品格坚毅，生命力顽强。"
  },
  {
    "name": "光明",
    "sex": "男女皆可",
    "desc": "取自“粉墙丹柱动光彩”的“光彩”和“欲以菲薄明其衷”的“明”。光明意为光亮、希望，寓意前途光明、正直磊落。"
  },
  {
    "name": "静心",
    "sex": "男女皆可",
    "desc": "取自“须臾静扫众峰出”的“静”和“潜心默祷若有应”的“心”。静心意为内心平静、专注，寓意为人沉稳内敛，专注于目标。"
  },
  {
    "name": "明月",
    "sex": "女性",
    "desc": "取自“欲以菲薄明其衷”的“明”和“星月掩映云朣胧”的“月”。明月象征皎洁、美好、宁静，寓意为人品性高洁，容貌秀美。"
  }
]