[
  {
    "name": "清江",
    "sex": "男女皆可",
    "desc": "取自诗句“南浦清江万里桥”中的连续词。意指心地纯净、思绪清晰，如清澈的江水般深远而顺遂，寓意品格高洁，生活平静美好。"
  },
  {
    "name": "万里",
    "sex": "男女皆可",
    "desc": "取自诗句“南浦清江万里桥”中的连续词。寓意拥有广阔的胸怀和远大的志向，前程似锦，未来可期，能实现远大的目标。"
  },
  {
    "name": "海内",
    "sex": "男",
    "desc": "取自诗句“海内风尘诸弟隔”中的连续词。意指名扬四海，拥有广泛的影响力和认可度，心怀天下，志在四方。"
  },
  {
    "name": "极目",
    "sex": "男",
    "desc": "取自诗句“跨马出郊时极目”中的连续词。寓意目光长远，视野开阔，善于观察和探索未知，有远见卓识。"
  },
  {
    "name": "海天",
    "sex": "男女皆可",
    "desc": "组合诗句“海内风尘诸弟隔”的首字“海”与“天涯涕泪一身遥”的首字“天”。寓意心胸开阔，拥有如海天般辽阔的视野和无尽的可能，境界高远。"
  },
  {
    "name": "南桥",
    "sex": "女",
    "desc": "组合诗句“南浦清江万里桥”的首字“南”与尾字“桥”。意境优美，如南国小桥流水般柔美而富有诗意，寓意连接、沟通与稳定，象征温柔与美好。"
  },
  {
    "name": "遥目",
    "sex": "男",
    "desc": "组合诗句“天涯涕泪一身遥”的尾字“遥”与“跨马出郊时极目”的尾字“目”。寓意目光深远，思虑周全，能够洞察事物发展的方向，有前瞻性。"
  }
]